flowstate_cli/__init__.py
flowstate_cli/api.py
flowstate_cli/auth.py
flowstate_cli/config.py
flowstate_cli/daemon.py
flowstate_cli/daemon_runner.py
flowstate_cli/data_manager.py
flowstate_cli/flow_mode.py
flowstate_cli/local_db.py
flowstate_cli/main.py
flowstate_cli/sync_engine.py
flowstate_cli/timer.py
flowstate_cli-1.3.dist-info/licenses/LICENSE
flowstate_cli-1.3.dist-info/METADATA
flowstate_cli-1.3.dist-info/WHEEL
flowstate_cli-1.3.dist-info/entry_points.txt
flowstate_cli-1.3.dist-info/top_level.txt
flowstate_cli-1.3.dist-info/RECORD
