Metadata-Version: 2.4
Name: flowstate-cli
Version: 1.3
Summary: Command-line productivity tool with task management and Pomodoro timers
Author-email: FlowState <sundancegithub@gmail.com>
License-Expression: MIT
Requires-Python: >=3.8
License-File: LICENSE
Requires-Dist: typer>=0.9.0
Requires-Dist: httpx>=0.25.0
Requires-Dist: rich>=13.0.0
Requires-Dist: plyer>=2.1.0
Requires-Dist: python-dotenv>=1.0.0
Requires-Dist: click>=8.1.0
Requires-Dist: sqlalchemy>=2.0.0
Requires-Dist: bcrypt>=4.0.0
Requires-Dist: PyJWT>=2.8.0
Dynamic: license-file
